predata/__init__.py
predata/coerce.py
predata/string.py
predata/typing.py
predata-2.1.0.dist-info/LICENSE.txt
predata-2.1.0.dist-info/WHEEL
predata-2.1.0.dist-info/METADATA
predata-2.1.0.dist-info/RECORD
